liveconfigs/__init__.py
liveconfigs/admin.py
liveconfigs/apps.py
liveconfigs/filters.py
liveconfigs/forms.py
liveconfigs/serializers.py
liveconfigs/signals.py
liveconfigs/tasks.py
liveconfigs/urls.py
liveconfigs/utils.py
liveconfigs/validators.py
liveconfigs/views.py
liveconfigs/management/__init__.py
liveconfigs/management/commands/__init__.py
liveconfigs/management/commands/delete_unused_configs.py
liveconfigs/management/commands/load_config.py
liveconfigs/migrations/0001_initial.py
liveconfigs/migrations/0002_historyevent.py
liveconfigs/migrations/0003_configrow_default_value.py
liveconfigs/migrations/0004_remove_configrow_tags.py
liveconfigs/migrations/0005_configrow_tags.py
liveconfigs/migrations/__init__.py
liveconfigs/models/__init__.py
liveconfigs/models/descriptors.py
liveconfigs/models/models.py
django_liveconfigs-1.0.6.1.dist-info/LICENSE
django_liveconfigs-1.0.6.1.dist-info/METADATA
django_liveconfigs-1.0.6.1.dist-info/WHEEL
django_liveconfigs-1.0.6.1.dist-info/top_level.txt
django_liveconfigs-1.0.6.1.dist-info/RECORD
