Metadata-Version: 2.1
Name: django-liveconfigs
Version: 1.0.6.1
Summary: Simple powerful and convenient configs for Django
Author-email: Evgenii Katsevman <eugene.katsevman@gmail.com>, Mihail Mayorov <mihail1-m1@yandex.ru>, Alexander Ignatov <goodwinsis@yandex.ru>, Alexander Mironov <mironov.miet@gmail.com>, Timur Timerkhanov <timurgrunge@gmail.com>, Ivan Shevyakov <iashevyakov@mail.ru>, Vladilav Nechaev <vladislavtv1@gmail.com>, Denis Dudnik <Denis.Dudnik@gmail.com>
Maintainer-email: Denis Dudnik <Denis.Dudnik@gmail.com>
License: Copyright (c) 2019-2024 F5Devs <https://f5devs.ru/>
Project-URL: Homepage, https://github.com/liveconfigs/django-liveconfigs
Project-URL: Documentation, https://github.com/liveconfigs/django-liveconfigs/blob/main/README.md
Project-URL: Repository, https://github.com/liveconfigs/django-liveconfigs
Project-URL: Changelog, https://github.com/liveconfigs/django-liveconfigs/blob/main/CHANGELOG.md
Project-URL: Bug Tracker, https://github.com/liveconfigs/django-liveconfigs/issues
Keywords: django,config,easy config,simple config,liveconfigs
Classifier: Development Status :: 5 - Production/Stable
Classifier: Framework :: Django :: 3.2
Classifier: Framework :: Django :: 4
Classifier: Framework :: Django :: 4.0
Classifier: Framework :: Django :: 4.1
Classifier: Framework :: Django :: 4.2
Classifier: Framework :: Django :: 5.0
Classifier: Intended Audience :: Developers
Classifier: License :: OSI Approved :: BSD License
Classifier: Operating System :: OS Independent
Classifier: Programming Language :: Python :: 3
Classifier: Programming Language :: Python :: 3.9
Classifier: Programming Language :: Python :: 3.10
Classifier: Programming Language :: Python :: 3.11
Classifier: Programming Language :: Python :: 3.12
Classifier: Topic :: Software Development :: Libraries :: Python Modules
Requires-Python: >=3.9
License-File: LICENSE
Requires-Dist: Django >=3.2
Requires-Dist: Django <=5.1
Requires-Dist: djangorestframework >=3.13.1
Requires-Dist: typeguard >=3.0.0
Requires-Dist: typeguard <5.0.0
Requires-Dist: django-import-export >=2.8.0
